README.md
setup.py
src/zone_api/__init__.py
src/zone_api/alert.py
src/zone_api/alert_manager.py
src/zone_api/audio_manager.py
src/zone_api/device_factory.py
src/zone_api/environment_canada.py
src/zone_api/music_streams.py
src/zone_api/platform_encapsulator.py
src/zone_api/security_manager.py
src/zone_api/time_utilities.py
src/zone_api/zone_parser.py
src/zone_api.egg-info/PKG-INFO
src/zone_api.egg-info/SOURCES.txt
src/zone_api.egg-info/dependency_links.txt
src/zone_api.egg-info/requires.txt
src/zone_api.egg-info/top_level.txt
src/zone_api/core/__init__.py
src/zone_api/core/action.py
src/zone_api/core/device.py
src/zone_api/core/event_info.py
src/zone_api/core/immutable_zone_manager.py
src/zone_api/core/neighbor.py
src/zone_api/core/zone.py
src/zone_api/core/zone_event.py
src/zone_api/core/zone_manager.py
src/zone_api/core/actions/__init__.py
src/zone_api/core/actions/alert_on_bad_computer_states.py
src/zone_api/core/actions/alert_on_entrance_activity.py
src/zone_api/core/actions/alert_on_external_door_left_open.py
src/zone_api/core/actions/alert_on_external_window_open.py
src/zone_api/core/actions/alert_on_failure_to_arm.py
src/zone_api/core/actions/alert_on_high_gas_level.py
src/zone_api/core/actions/alert_on_humidity_out_of_range.py
src/zone_api/core/actions/alert_on_inactive_devices.py
src/zone_api/core/actions/alert_on_rain_or_snow_during_the_day.py
src/zone_api/core/actions/alert_on_security_alarm_triggered.py
src/zone_api/core/actions/alert_on_temperature_out_of_range.py
src/zone_api/core/actions/alert_on_water_leak.py
src/zone_api/core/actions/announce_morning_weather_and_play_music.py
src/zone_api/core/actions/arm_after_front_door_closed.py
src/zone_api/core/actions/arm_if_no_movement.py
src/zone_api/core/actions/arm_stay_in_the_night.py
src/zone_api/core/actions/change_thermostat_based_on_security_arm_mode.py
src/zone_api/core/actions/control_music_player.py
src/zone_api/core/actions/disarm_on_internal_motion.py
src/zone_api/core/actions/disarm_when_garage_door_is_open.py
src/zone_api/core/actions/manage_plugs.py
src/zone_api/core/actions/play_mindfulness_bell.py
src/zone_api/core/actions/play_music_at_dinner_time.py
