Metadata-Version: 2.1
Name: zone-api
Version: 0.2.1
Summary: Reusable Home Automation rules.
Home-page: https://github.com/yfaway/zone-apis
Author: YF
License: MIT
Download-URL: https://github.com/yfaway/zone-apis/archive/refs/tags/v_01.tar.gz
Keywords: zone api,home automation,openhab,habapp
Platform: UNKNOWN
Classifier: Development Status :: 3 - Alpha
Classifier: Intended Audience :: Developers
Classifier: Topic :: Home Automation
Classifier: License :: OSI Approved :: MIT License
Classifier: Operating System :: OS Independent
Classifier: Programming Language :: Python :: 3.7
Classifier: Programming Language :: Python :: 3.8
Classifier: Programming Language :: Python :: 3.9
Classifier: Programming Language :: Python :: 3 :: Only
